hackaclime/__init__.py
hackaclime/hackaclime.cfg
hackaclime/hackaclime.py
hackaclime-0.1.9.dist-info/licenses/LICENSE
hackaclime-0.1.9.dist-info/WHEEL
hackaclime-0.1.9.dist-info/entry_points.txt
hackaclime-0.1.9.dist-info/METADATA
hackaclime-0.1.9.dist-info/RECORD
