Metadata-Version: 2.4
Name: hackaclime
Version: 0.1.9
Summary: CLI utility to read Hack Club's Hackatime time tracking API
License-Expression: GPL-3.0-only
License-File: LICENSE
Requires-Dist: requests>=2.32.5
Requires-Dist: schedule>=1.2.2
Requires-Python: >=3.12
